pypaas/__init__.py
pypaas/task.py
pypaas-0.1.0.dist-info/METADATA
pypaas-0.1.0.dist-info/WHEEL
pypaas-0.1.0.dist-info/top_level.txt
pypaas-0.1.0.dist-info/RECORD
